golden_ratio_stats/__init__.py
golden_ratio_stats/golden_ratio_approch.py
golden_ratio_stats-0.1.2.dist-info/METADATA
golden_ratio_stats-0.1.2.dist-info/WHEEL
golden_ratio_stats-0.1.2.dist-info/top_level.txt
golden_ratio_stats-0.1.2.dist-info/RECORD
