Metadata-Version: 2.1
Name: golden-ratio-stats
Version: 0.1.2
Summary: Golden Ratio in Statistics
Home-page: https://github.com/serhateerdem
Author: Serhat Erdem
Author-email: erdemserhat1994@gmail.com
Classifier: Programming Language :: Python :: 3.9
Requires-Python: >=3.9
Requires-Dist: numpy (>=1.23.4)
Requires-Dist: pandas (>=1.5.1)
